telemoma/__init__.py
telemoma/configs/__init__.py
telemoma/configs/base_config.py
telemoma/configs/only_keyboard.py
telemoma/configs/only_mobile_phone.py
telemoma/configs/only_spacemouse.py
telemoma/configs/only_vision.py
telemoma/configs/only_vr.py
telemoma/configs/vr_hand_vision_base.py
telemoma/human_interface/__init__.py
telemoma/human_interface/keyboard.py
telemoma/human_interface/mobile_phone.py
telemoma/human_interface/oculus.py
telemoma/human_interface/spacemouse.py
telemoma/human_interface/teleop_core.py
telemoma/human_interface/teleop_policy.py
telemoma/human_interface/vision.py
telemoma/utils/__init__.py
telemoma/utils/camera_utils.py
telemoma/utils/general_utils.py
telemoma/utils/ros_utils.py
telemoma/utils/transformations.py
telemoma/utils/vision_teleop_utils.py
telemoma-0.3.0.dist-info/METADATA
telemoma-0.3.0.dist-info/WHEEL
telemoma-0.3.0.dist-info/top_level.txt
telemoma-0.3.0.dist-info/RECORD
