Metadata-Version: 2.4
Name: telemoma
Version: 0.3.0
Summary: A modular and versatile teleoperation system for mobile manipulation
Home-page: https://github.com/UT-Austin-RobIn/telemoma
Author: Shivin Dass
Author-email: shivindass@gmail.com
Requires-Python: >=3
Requires-Dist: numpy
Requires-Dist: opencv-python
Requires-Dist: mediapipe
Requires-Dist: scipy
Requires-Dist: pyrealsense2
Requires-Dist: pyspacemouse
Requires-Dist: pynput
Requires-Dist: matplotlib
Requires-Dist: gymnasium
Dynamic: author
Dynamic: author-email
Dynamic: description
Dynamic: description-content-type
Dynamic: home-page
Dynamic: requires-dist
Dynamic: requires-python
Dynamic: summary
